py_minisam/__about__.py
py_minisam/__init__.py
py_minisam/auto_diff.py
py_minisam/factor_graph.py
py_minisam/problem.py
py_minisam/optimizer/__init__.py
py_minisam/optimizer/base_optimizer.py
py_minisam/optimizer/gauss_newton_optimizer.py
py_minisam/optimizer/levenberg_marquardt_optimizer.py
py_minisam-0.2.0.dist-info/METADATA
py_minisam-0.2.0.dist-info/WHEEL
py_minisam-0.2.0.dist-info/licenses/LICENSE
py_minisam-0.2.0.dist-info/RECORD
