Metadata-Version: 2.1
Name: py-minisam
Version: 0.2.0
Project-URL: Documentation, https://github.com/powei-lin/py-minisam#readme
Project-URL: Issues, https://github.com/powei-lin/py-minisam/issues
Project-URL: Source, https://github.com/powei-lin/py-minisam
Author-email: Powei Lin <poweilin1994@gmail.com>
License-Expression: MIT
License-File: LICENSE
Classifier: Development Status :: 4 - Beta
Classifier: Programming Language :: Python
Classifier: Programming Language :: Python :: 3.8
Classifier: Programming Language :: Python :: 3.9
Classifier: Programming Language :: Python :: 3.10
Classifier: Programming Language :: Python :: 3.11
Classifier: Programming Language :: Python :: 3.12
Classifier: Programming Language :: Python :: Implementation :: CPython
Classifier: Programming Language :: Python :: Implementation :: PyPy
Requires-Python: >=3.8
Requires-Dist: scipy
